Belrub/__init__.py
Belrub/rubel.py
Belrub/encryption/__init__.py
Belrub_2.1.1-2.1.1.dist-info/METADATA
Belrub_2.1.1-2.1.1.dist-info/WHEEL
Belrub_2.1.1-2.1.1.dist-info/top_level.txt
Belrub_2.1.1-2.1.1.dist-info/RECORD
