Metadata-Version: 2.1
Name: Belrub-2.1.1
Version: 2.1.1
Summary: This is a Library for robots in Rubika
Home-page: UNKNOWN
Author: Mamad Belectron
Author-email: UNKNOWN
License: UNKNOWN
Keywords: python,rubika,Belrub,rubel,Rubika,belectron,robika,robot
Platform: UNKNOWN
Classifier: Development Status :: 3 - Alpha
Classifier: Intended Audience :: Education
Classifier: Programming Language :: Python :: 2
Classifier: Programming Language :: Python :: 3
Requires-Dist: pycryptodome (==3.16.0)
Requires-Dist: Pillow (==9.4.0)
